AUTHORS
LICENSE
MANIFEST.in
README.md
pyproject.toml
requirements.txt
setup.py
ANNarchy/__init__.py
ANNarchy.egg-info/PKG-INFO
ANNarchy.egg-info/SOURCES.txt
ANNarchy.egg-info/dependency_links.txt
ANNarchy.egg-info/requires.txt
ANNarchy.egg-info/top_level.txt
ANNarchy/core/ConnectorMethods.py
ANNarchy/core/Constant.py
ANNarchy/core/Dendrite.py
ANNarchy/core/Global.py
ANNarchy/core/IO.py
ANNarchy/core/Monitor.py
ANNarchy/core/Network.py
ANNarchy/core/Neuron.py
ANNarchy/core/Population.py
ANNarchy/core/PopulationView.py
ANNarchy/core/Projection.py
ANNarchy/core/Random.py
ANNarchy/core/Simulate.py
ANNarchy/core/Synapse.py
ANNarchy/core/Utils.py
ANNarchy/core/__init__.py
ANNarchy/cython_ext/Connector.pxd
ANNarchy/cython_ext/Connector.pyx
ANNarchy/cython_ext/Coordinates.pxd
ANNarchy/cython_ext/Coordinates.pyx
ANNarchy/cython_ext/Transformations.pyx
ANNarchy/cython_ext/__init__.pxd
ANNarchy/cython_ext/__init__.py
ANNarchy/extensions/__init__.py
ANNarchy/extensions/ann_to_snn_conversion/ANNtoSNNConverter.py
ANNarchy/extensions/ann_to_snn_conversion/InputEncoding.py
ANNarchy/extensions/ann_to_snn_conversion/ReadOut.py
ANNarchy/extensions/ann_to_snn_conversion/__init__.py
ANNarchy/extensions/bold/AccProjection.py
ANNarchy/extensions/bold/BoldModel.py
ANNarchy/extensions/bold/BoldMonitor.py
ANNarchy/extensions/bold/NormProjection.py
ANNarchy/extensions/bold/PredefinedModels.py
ANNarchy/extensions/bold/__init__.py
ANNarchy/extensions/convolution/Convolve.py
ANNarchy/extensions/convolution/ConvolveTemplate.py
ANNarchy/extensions/convolution/Copy.py
ANNarchy/extensions/convolution/CopyTemplate.py
ANNarchy/extensions/convolution/Pooling.py
ANNarchy/extensions/convolution/PoolingTemplate.py
ANNarchy/extensions/convolution/Transpose.py
ANNarchy/extensions/convolution/Utils.py
ANNarchy/extensions/convolution/__init__.py
ANNarchy/extensions/diagonal/DiagonalProjection.py
ANNarchy/extensions/diagonal/__init__.py
ANNarchy/extensions/hybrid/HybridPopulation.py
ANNarchy/extensions/hybrid/__init__.py
ANNarchy/extensions/image/ImagePopulation.py
ANNarchy/extensions/image/__init__.py
ANNarchy/extensions/tensorboard/Logger.py
