Metadata-Version: 2.2
Name: ANNarchy
Version: 4.8.2.5
Summary: Artificial Neural Networks architect
Author-email: Julien Vitay <julien.vitay@informatik.tu-chemnitz.de>, Helge Dinkelbach <helge-uelo.dinkelbach@informatik.tu-chemnitz.de>, Fred Hamker <fred.hamker@informatik.tu-chemnitz.de>
License: GPLv2+
Project-URL: Documentation, https://annarchy.github.io
Project-URL: Issues, https://github.com/ANNarchy/ANNarchy/issues
Project-URL: Source, https://github.com/ANNarchy/ANNarchy
Keywords: neural simulator
Classifier: Development Status :: 5 - Production/Stable
Classifier: Environment :: Console
Classifier: Intended Audience :: Science/Research
Classifier: Programming Language :: Python
Classifier: Programming Language :: Python :: 3.10
Classifier: Programming Language :: Python :: 3.11
Classifier: Programming Language :: Python :: 3.12
Classifier: Programming Language :: Python :: Implementation :: CPython
Requires-Python: >=3.10
License-File: LICENSE
License-File: AUTHORS
Requires-Dist: setuptools
Requires-Dist: cython
Requires-Dist: numpy
Requires-Dist: sympy
Requires-Dist: scipy
Requires-Dist: matplotlib
Requires-Dist: tqdm
Requires-Dist: h5py
Requires-Dist: lxml
